{
  "id": "feliz-deserto",
  "nome": "FELIZ DESERTO",
  "detalhe": {
    "2020": {
      "num_diarios": 61,
      "num_nomeacoes": 0,
      "num_exoneracoes": 0
    },
    "2021": {
      "num_diarios": 59,
      "num_nomeacoes": 37,
      "num_exoneracoes": 1
    },
    "2022": {
      "num_diarios": 73,
      "num_nomeacoes": 0,
      "num_exoneracoes": 1
    },
    "2023": {
      "num_diarios": 21,
      "num_nomeacoes": 1,
      "num_exoneracoes": 0
    }
  },
  "resumo": {
    "num_diarios": 214,
    "num_exoneracoes": 2,
    "num_nomeacoes": 38
  }
}